xbahn
