Metadata-Version: 1.1
Name: xbahn
Version: 1.99.1
Summary: xbahn description
Home-page: https://github.com/20c/xbahn
Author: 20C
Author-email: code@20c.com
License: LICENSE.txt
Download-URL: https://github.com/20c/xbahn/1.99.1
Platform: UNKNOWN
Classifier: Development Status :: 4 - Beta
Classifier: Programming Language :: Python :: 2.7
Classifier: Programming Language :: Python :: 3.4
Classifier: License :: OSI Approved :: Apache Software License
